Metadata-Version: 1.2
Name: amegaparser
Version: 0.1
Summary: Converter for (old) AmegaView binary data crash files.
Home-page: UNKNOWN
Author: tekulvw
License: GPLv3
Platform: UNKNOWN
Classifier: Development Status :: 4 - Beta
Classifier: Environment :: Console
Classifier: License :: OSI Approved :: GNU General Public License v3 (GPLv3)
Classifier: Operating System :: OS Independent
Classifier: Programming Language :: Python :: 3.6
Requires-Python: >=3.6,<3.7
